full_adder.v
// full_adder.v
module full_adder (
    input  wire a,
    input  wire b,
    input  wire cin,
    output wire sum,
    output wire cout
);
    assign {cout, sum} = a + b + cin;
endmodule

tb_full_adder.v
// tb_full_adder.v
`timescale 1ns/1ps

module tb_full_adder;
    reg a, b, cin;
    wire sum, cout;

    // instantiate full adder
    full_adder uut (
        .a(a), .b(b), .cin(cin),
        .sum(sum), .cout(cout)
    );

    initial begin
        $dumpfile("dump.vcd");   // waveform file
        $dumpvars(0, tb_full_adder);

        // try all combinations of a, b, cin
        {a,b,cin} = 3'b000; #10;
        {a,b,cin} = 3'b001; #10;
        {a,b,cin} = 3'b010; #10;
        {a,b,cin} = 3'b011; #10;
        {a,b,cin} = 3'b100; #10;
        {a,b,cin} = 3'b101; #10;
        {a,b,cin} = 3'b110; #10;
        {a,b,cin} = 3'b111; #10;

        $finish;
    end
endmodule

dump.vcd
$date
	Fri Sep 05 21:35:21 2025
$end
$version
	Icarus Verilog
$end
$timescale
	1ps
$end
$scope module tb_full_adder $end
$var wire 1 ! sum $end
$var wire 1 " cout $end
$var reg 1 # a $end
$var reg 1 $ b $end
$var reg 1 % cin $end
$scope module uut $end
$var wire 1 # a $end
$var wire 1 $ b $end
$var wire 1 % cin $end
$var wire 1 ! sum $end
$var wire 1 " cout $end
$upscope $end
$upscope $end
$enddefinitions $end
$comment Show the parameter values. $end
$dumpall
$end
#0
$dumpvars
0%
0$
0#
0"
0!
$end
#10000
1!
1%
#20000
1$
0%
#30000
0!
1"
1%
#40000
1!
0"
1#
0$
0%
#50000
0!
1"
1%
#60000
1$
0%
#70000
1!
1%
